Lab07/ALU.v
`define AND   4'b0000
`define OR    4'b0001
`define ADD   4'b0010
`define SUB   4'b0110
`define PassB 4'b0111


module ALU(BusW, BusA, BusB, ALUCtrl, Zero);
    
    output  [63:0] BusW;
    input   [63:0] BusA, BusB;
    input   [3:0] ALUCtrl;
    output  Zero;
    
    reg     [63:0] BusW;
    
    always @(ALUCtrl or BusA or BusB) begin
        case(ALUCtrl)
          `AND:   BusW = (BusA & BusB);
	  `OR:    BusW = (BusA | BusB);
	  `ADD:   BusW = (BusA + BusB);
	  `SUB:   BusW = (BusA - BusB);
	  `PassB: BusW = BusB;
	  default: BusW = 64'h6969696969696969;
        endcase
    end

   assign Zero = (BusW == 64'h0) ? 1'b1 : 1'b0;    // Zero = (BusW == 0)
endmodule

Lab07/ALUTest.v
`timescale 1ns / 1ps

////////////////////////////////////////////////////////////////////////////////
// Company: 
// Engineer:
//
// Create Date:   10:02:47 03/05/2009
// Design Name:   ALU
// Module Name:   E:/350/Lab8/ALU/ALUTest.v
// Project Name:  ALU
// Target Device:  
// Tool versions:  
// Description: 
//
// Verilog Test Fixture created by ISE for module: ALU
//
// Dependencies:
// 
// Revision:
// Revision 0.01 - File Created
// Additional Comments:
// 
////////////////////////////////////////////////////////////////////////////////

`define STRLEN 12 // was 32
module ALUTest_v;

   initial begin
      $dumpfile("ALUTest.vcd");
      $dumpvars(0, ALUTest_v);
   end

	task passTest;
	   input gotZero;
	   input [63:0] actualOut;
	   input 	expZero;
	   input [63:0] expectedOut;
	   input [`STRLEN*8:0] testType;
	   inout [7:0] passed;

	       if (actualOut == expectedOut) begin
                   if (gotZero == expZero) begin
                       $display("%s :: Passed", testType); passed = passed + 1;
		   end
	           else $display("%s :: Failed:\n\tExpected zero = %x\n\t\tGot: %x", testType, expZero, gotZero);
	       end
	       else $display("%s :: Failed:\n\tExpected BusW = %x\n\t\tGot: %x", testType, expectedOut, actualOut);
	endtask
	
	task allPassed;
		input [7:0] passed;
		input [7:0] numTests;
		
		if(passed == numTests) $display ("All tests passed");
		else $display("Some tests failed");
	endtask

	// Inputs
	reg [63:0] BusA;
	reg [63:0] BusB;
	reg [3:0] ALUCtrl;
	reg [7:0] passed;

	// Outputs
	wire [63:0] BusW;
	wire Zero;

	// Instantiate the Unit Under Test (UUT)
	ALU uut (
		.BusW(BusW), 
		.Zero(Zero), 
		.BusA(BusA), 
		.BusB(BusB), 
		.ALUCtrl(ALUCtrl)
	);

	initial begin
		// Initialize Inputs
		BusA = 0;
		BusB = 0;
		ALUCtrl = 0;
		passed = 0;

                // Here is one example test vector, testing the ADD instruction:
		{ALUCtrl, BusA, BusB} = {4'h0, 64'h200, 64'h150}; #40; passTest(Zero, BusW, 1'b1, 64'h0, "AND1", passed);
		{ALUCtrl, BusA, BusB} = {4'h0, 64'h700, 64'h700}; #40; passTest(Zero, BusW, 1'b0, 64'h700, "AND2", passed);
		{ALUCtrl, BusA, BusB} = {4'h0, 64'h1234, 64'h4321}; #40; passTest(Zero, BusW, 1'b0, 64'h220, "AND3", passed);
		{ALUCtrl, BusA, BusB} = {4'h1, 64'h200, 64'h150}; #40; passTest(Zero, BusW, 1'b0, 64'h350, "OR1", passed);
		{ALUCtrl, BusA, BusB} = {4'h1, 64'h700, 64'h700}; #40; passTest(Zero, BusW, 1'b0, 64'h700, "OR2", passed);
		{ALUCtrl, BusA, BusB} = {4'h1, 64'h1234, 64'h4321}; #40; passTest(Zero, BusW, 1'b0, 64'h5335, "OR3", passed);
		{ALUCtrl, BusA, BusB} = {4'h2, 64'h200, 64'h150}; #40; passTest(Zero, BusW, 1'b0, 64'h350, "ADD1", passed);
		{ALUCtrl, BusA, BusB} = {4'h2, 64'h700, 64'h700}; #40; passTest(Zero, BusW, 1'b0, 64'he00, "ADD2", passed);
		{ALUCtrl, BusA, BusB} = {4'h2, 64'h1234, 64'h4321}; #40; passTest(Zero, BusW, 1'b0, 64'h5555, "ADD3", passed);
		{ALUCtrl, BusA, BusB} = {4'h6, 64'h200, 64'h150}; #40; passTest(Zero, BusW, 1'b0, 64'hb0, "SUB1", passed);
		{ALUCtrl, BusA, BusB} = {4'h6, 64'h700, 64'h700}; #40; passTest(Zero, BusW, 1'b1, 64'h0, "SUB2", passed);
		{ALUCtrl, BusA, BusB} = {4'h6, 64'h1234, 64'h4321}; #40; passTest(Zero, BusW, 1'b0, 64'hffffffffffffcf13, "SUB3", passed);
		{ALUCtrl, BusA, BusB} = {4'h7, 64'h200, 64'h150}; #40; passTest(Zero, BusW, 1'b0, 64'h150, "PassB1", passed);
		{ALUCtrl, BusA, BusB} = {4'h7, 64'h700, 64'h700}; #40; passTest(Zero, BusW, 1'b0, 64'h700, "PassB2", passed);
		{ALUCtrl, BusA, BusB} = {4'h7, 64'h1234, 64'h4321}; #40; passTest(Zero, BusW, 1'b0, 64'h4321, "PassB3", passed);
		//Reformate and add your test vectors from the prelab here following the example of the testvector above.	


		allPassed(passed, 15);
	end
      
endmodule

Lab07/ALUTest.vcd
$date
	Wed Nov  2 18:57:22 2022
$end
$version
	Icarus Verilog
$end
$timescale
	1ps
$end
$scope module ALUTest_v $end
$var wire 1 ! Zero $end
$var wire 64 " BusW [63:0] $end
$var reg 4 # ALUCtrl [3:0] $end
$var reg 64 $ BusA [63:0] $end
$var reg 64 % BusB [63:0] $end
$var reg 8 & passed [7:0] $end
$scope module uut $end
$var wire 4 ' ALUCtrl [3:0] $end
$var wire 64 ( BusA [63:0] $end
$var wire 64 ) BusB [63:0] $end
$var wire 1 ! Zero $end
$var reg 64 * BusW [63:0] $end
$upscope $end
$scope task allPassed $end
$var reg 8 + numTests [7:0] $end
$var reg 8 , passed [7:0] $end
$upscope $end
$scope task passTest $end
$var reg 64 - actualOut [63:0] $end
$var reg 1 . expZero $end
$var reg 64 / expectedOut [63:0] $end
$var reg 1 0 gotZero $end
$var reg 8 1 passed [7:0] $end
$var reg 97 2 testType [96:0] $end
$upscope $end
$upscope $end
$enddefinitions $end
#0
$dumpvars
bx 2
bx 1
x0
bx /
x.
bx -
bx ,
bx +
b0 *
b101010000 )
b1000000000 (
b0 '
b0 &
b101010000 %
b1000000000 $
b0 #
b0 "
1!
$end
#40000
0!
b11100000000 "
b11100000000 *
b11100000000 $
b11100000000 (
b11100000000 %
b11100000000 )
b1 &
b1 1
b1000001010011100100010000110001 2
b0 /
1.
b0 -
10
#80000
b1000100000 "
b1000100000 *
b1001000110100 $
b1001000110100 (
b100001100100001 %
b100001100100001 )
b10 &
b10 1
b1000001010011100100010000110010 2
b11100000000 /
0.
b11100000000 -
00
#120000
b1101010000 "
b1101010000 *
b1 #
b1 '
b1000000000 $
b1000000000 (
b101010000 %
b101010000 )
b11 &
b11 1
b1000001010011100100010000110011 2
b1000100000 /
b1000100000 -
#160000
b11100000000 "
b11100000000 *
b11100000000 $
b11100000000 (
b11100000000 %
b11100000000 )
b100 &
b100 1
b10011110101001000110001 2
b1101010000 /
b1101010000 -
#200000
b101001100110101 "
b101001100110101 *
b1001000110100 $
b1001000110100 (
b100001100100001 %
b100001100100001 )
b101 &
b101 1
b10011110101001000110010 2
b11100000000 /
b11100000000 -
#240000
b1101010000 "
b1101010000 *
b10 #
b10 '
b1000000000 $
b1000000000 (
b101010000 %
b101010000 )
b110 &
b110 1
b10011110101001000110011 2
b101001100110101 /
b101001100110101 -
#280000
b111000000000 "
b111000000000 *
b11100000000 $
b11100000000 (
b11100000000 %
b11100000000 )
b111 &
b111 1
b1000001010001000100010000110001 2
b1101010000 /
b1101010000 -
#320000
b101010101010101 "
b101010101010101 *
b1001000110100 $
b1001000110100 (
b100001100100001 %
b100001100100001 )
b1000 &
b1000 1
b1000001010001000100010000110010 2
b111000000000 /
b111000000000 -
#360000
b10110000 "
b10110000 *
b110 #
b110 '
b1000000000 $
b1000000000 (
b101010000 %
b101010000 )
b1001 &
b1001 1
b1000001010001000100010000110011 2
b101010101010101 /
b101010101010101 -
#400000
1!
b0 "
b0 *
b11100000000 $
b11100000000 (
b11100000000 %
b11100000000 )
b1010 &
b1010 1
b1010011010101010100001000110001 2
b10110000 /
b10110000 -
#440000
0!
b1111111111111111111111111111111111111111111111111100111100010011 "
b1111111111111111111111111111111111111111111111111100111100010011 *
b1001000110100 $
b1001000110100 (
b100001100100001 %
b100001100100001 )
b1011 &
b1011 1
b1010011010101010100001000110010 2
b0 /
1.
b0 -
10
#480000
b101010000 "
b101010000 *
b111 #
b111 '
b1000000000 $
b1000000000 (
b101010000 %
b101010000 )
b1100 &
b1100 1
b1010011010101010100001000110011 2
b1111111111111111111111111111111111111111111111111100111100010011 /
0.
b1111111111111111111111111111111111111111111111111100111100010011 -
00
#520000
b11100000000 "
b11100000000 *
b11100000000 $
b11100000000 (
b11100000000 %
b11100000000 )
b1101 &
b1101 1
b10100000110000101110011011100110100001000110001 2
b101010000 /
b101010000 -
#560000
b100001100100001 "
b100001100100001 *
b1001000110100 $
b1001000110100 (
b100001100100001 %
b100001100100001 )
b1110 &
b1110 1
b10100000110000101110011011100110100001000110010 2
b11100000000 /
b11100000000 -
#600000
b1111 +
b1111 ,
b1111 &
b1111 1
b10100000110000101110011011100110100001000110011 2
b100001100100001 /
b100001100100001 -
