Lab07/SignExtender.v
`define I   3'b000
`define D   3'b001
`define B   3'b010
`define CB  3'b011
`define IM  3'b100

module SignExtender(BusImm, Input, Ctrl); 
   output [63:0] BusImm; 
   input [25:0]  Input; 
   input [2:0]	 Ctrl; 
   
   wire 	 extBit;

   wire [6:0] 	 shift;
   wire [63:0]   movz;

   assign shift = Input[22:21] << 4;     // Get shift * 16
   assign movz  = Input[20:5] << shift;  // movz_imm << shift

   assign extBit =
		  (Ctrl ==  `I) ? Input[21] : // I
		  (Ctrl ==  `D) ? Input[20] : // D
		  (Ctrl ==  `B) ? Input[25] : // B
          (Ctrl == `CB) ? Input[23] : // CB
          1'b0;                       // IM and default

   
   assign BusImm =
		  (Ctrl ==  `I) ? {{52{extBit}}, Input[21:10]} : // I
		  (Ctrl ==  `D) ? {{55{extBit}}, Input[20:12]} : // D
		  (Ctrl ==  `B) ? {{38{extBit}}, Input[25: 0]} : // B
          (Ctrl == `CB) ? {{45{extBit}}, Input[23: 5]} : // CB
          (Ctrl == `IM) ? {movz} : {64'b0};  // Default BusImm = 0
endmodule

Lab07/SignExtenderTest.v
`timescale 1ns / 1ps

////////////////////////////////////////////////////////////////////////////////
// Company: 
// Engineer:
//
// Create Date:   10:02:47 03/05/2009
// Design Name:   ALU
// Module Name:   E:/350/Lab7/SignExtenderTest.v
// Project Name:  SignExtender
// Target Device:  
// Tool versions:  
// Description: 
//
// Verilog Test Fixture created by ISE for module: SignExtender
//$display ("%s passed", testType)
// Dependencies:
// 
// Revision:
// Revision 0.01 - File Created
// Additional Comments:
// 
////////////////////////////////////////////////////////////////////////////////

`define STRLEN 32
module SignExtenderTest_v;

   initial begin
      $dumpfile("SignExtenderTest.vcd");
      $dumpvars(0, SignExtenderTest_v);
   end
	task passTest;
		input [63:0] actualOut, expectedOut;
		input [`STRLEN*8:0] testType;
		inout [7:0] passed;
	
		if(actualOut == expectedOut) begin $display ("\tpassed\t%s", testType); passed = passed + 1; end
		else $display ("\tfailed\t%s\n\t: %x should be %x", testType, actualOut, expectedOut);
	endtask
	
	task allPassed;
		input [7:0] passed;
		input [7:0] numTests;
		
		if(passed == numTests) $display ("All tests passed");
		else $display("Some tests failed");
	endtask

	// Inputs
        reg [25:0]  Input;
        reg [2:0]  Ctrl;
	reg [7:0] passed;

	// Outputs
	wire [63:0] BusImm;

	// Instantiate the Unit Under Test (UUT)
	SignExtender uut (
		.BusImm(BusImm),
		.Input(Input),
		.Ctrl(Ctrl)
	);

	initial begin
		// Initialize Inputs
		Input = 0;
		Ctrl = 0;
		passed = 0;

                // Here is one example test vector, testing the ADD instruction:
	        $display ("8 Test Vectors:");
			{Input, Ctrl} = {26'h444, 3'h0}; #40; passTest({BusImm}, 64'h1, "I  :: Positive", passed);
	        {Input, Ctrl} = {26'hfff73ff, 3'h0}; #40; passTest({BusImm}, 64'hffffffffffffffdc, "I  :: Negative", passed);
	        {Input, Ctrl} = {26'h1234, 3'h1}; #40; passTest({BusImm}, 64'h1, "D  :: Positive", passed);
	        {Input, Ctrl} = {26'hffdcfff, 3'h1}; #40; passTest({BusImm}, 64'hffffffffffffffdc, "D  :: Negative", passed);
	        {Input, Ctrl} = {26'h24, 3'h2}; #40; passTest({BusImm}, 64'h24, "B  :: Positive", passed);
	        {Input, Ctrl} = {26'hfffffdc, 3'h2}; #40; passTest({BusImm}, 64'hffffffffffffffdc, "B  :: Negative", passed);
	        {Input, Ctrl} = {26'h20, 3'h3}; #40; passTest({BusImm}, 64'h1, "CB :: Positive", passed);
	        {Input, Ctrl} = {26'hffffb9f, 3'h3}; #40; passTest({BusImm}, 64'hffffffffffffffdc, "CB :: Negative", passed);
			// Tests for new operation in Lab09: MOVZ
			{Input, Ctrl} = {26'h399c62f, 3'h4}; #40; passTest({BusImm}, 64'hce31, "IM :: Test #1 [ce31 << 0]", passed);
			{Input, Ctrl} = {26'h3b9c62f, 3'h4}; #40; passTest({BusImm}, 64'hce310000, "IM :: Test #2 [ce31 << 16]", passed);
			{Input, Ctrl} = {26'h3d9c62f, 3'h4}; #40; passTest({BusImm}, 64'hce3100000000, "IM :: Test #3 [ce31 << 32]", passed);
			{Input, Ctrl} = {26'h3f9c62f, 3'h4}; #40; passTest({BusImm}, 64'hce31000000000000, "IM :: Test #4 [ce31 << 48]", passed);
			{Input, Ctrl} = {26'h101418c, 3'h4}; #40; passTest({BusImm}, 64'ha0c, "IM :: Test #5 [a0c << 0]", passed);
			{Input, Ctrl} = {26'h121418c, 3'h4}; #40; passTest({BusImm}, 64'ha0c0000, "IM :: Test #6 [a0c << 16]", passed);
			{Input, Ctrl} = {26'h141418c, 3'h4}; #40; passTest({BusImm}, 64'ha0c00000000, "IM :: Test #7 [a0c << 32]", passed);
			{Input, Ctrl} = {26'h161418c, 3'h4}; #40; passTest({BusImm}, 64'ha0c000000000000, "IM :: Test #8 [a0c << 48]", passed);
			{Input, Ctrl} = {26'h305c7b9, 3'h4}; #40; passTest({BusImm}, 64'h2e3d, "IM :: Test #9 [2e3d << 0]", passed);
			{Input, Ctrl} = {26'h325c7b9, 3'h4}; #40; passTest({BusImm}, 64'h2e3d0000, "IM :: Test #10 [2e3d << 16]", passed);
			{Input, Ctrl} = {26'h345c7b9, 3'h4}; #40; passTest({BusImm}, 64'h2e3d00000000, "IM :: Test #11 [2e3d << 32]", passed);
			{Input, Ctrl} = {26'h365c7b9, 3'h4}; #40; passTest({BusImm}, 64'h2e3d000000000000, "IM :: Test #12 [2e3d << 48]", passed);
	        
		//Reformate and add your test vectors from the prelab here following the example of the testvector above.	


		allPassed(passed, 20);
	end  

      
endmodule

Lab07/SignExtenderTest.vcd
$date
	Tue Nov 29 18:40:43 2022
$end
$version
	Icarus Verilog
$end
$timescale
	1ps
$end
$scope module SignExtenderTest_v $end
$var wire 64 ! BusImm [63:0] $end
$var reg 3 " Ctrl [2:0] $end
$var reg 26 # Input [25:0] $end
$var reg 8 $ passed [7:0] $end
$scope module uut $end
$var wire 3 % Ctrl [2:0] $end
$var wire 26 & Input [25:0] $end
$var wire 7 ' shift [6:0] $end
$var wire 64 ( movz [63:0] $end
$var wire 1 ) extBit $end
$var wire 64 * BusImm [63:0] $end
$upscope $end
$scope task allPassed $end
$var reg 8 + numTests [7:0] $end
$var reg 8 , passed [7:0] $end
$upscope $end
$scope task passTest $end
$var reg 64 - actualOut [63:0] $end
$var reg 64 . expectedOut [63:0] $end
$var reg 8 / passed [7:0] $end
$var reg 257 0 testType [256:0] $end
$upscope $end
$upscope $end
$enddefinitions $end
#0
$dumpvars
bx 0
bx /
bx .
bx -
bx ,
bx +
b1 *
0)
b100010 (
b0 '
b10001000100 &
b0 %
b0 $
b10001000100 #
b0 "
b1 !
$end
#40000
b110000 '
1)
b1111111111111111111111111111111111111111111111111111111111011100 !
b1111111111111111111111111111111111111111111111111111111111011100 *
b1111101110011111000000000000000000000000000000000000000000000000 (
b11111111110111001111111111 #
b11111111110111001111111111 &
b1 $
b1 /
b100100100100000001000000011101000111010001000000101000001101111011100110110100101110100011010010111011001100101 0
b1 .
b1 -
#80000
0)
b0 '
b10010001 (
b1 !
b1 *
b1001000110100 #
b1001000110100 &
b1 "
b1 %
b10 $
b10 /
b100100100100000001000000011101000111010001000000100111001100101011001110110000101110100011010010111011001100101 0
b1111111111111111111111111111111111111111111111111111111111011100 .
b1111111111111111111111111111111111111111111111111111111111011100 -
#120000
1)
b1111111111111111111111111111111111111111111111111111111111011100 !
b1111111111111111111111111111111111111111111111111111111111011100 *
b110000 '
b1110111001111111000000000000000000000000000000000000000000000000 (
b11111111011100111111111111 #
b11111111011100111111111111 &
b11 $
b11 /
b100010000100000001000000011101000111010001000000101000001101111011100110110100101110100011010010111011001100101 0
b1 .
b1 -
#160000
0)
b0 '
b100100 !
b100100 *
b1 (
b100100 #
b100100 &
b10 "
b10 %
b100 $
b100 /
b100010000100000001000000011101000111010001000000100111001100101011001110110000101110100011010010111011001100101 0
b1111111111111111111111111111111111111111111111111111111111011100 .
b1111111111111111111111111111111111111111111111111111111111011100 -
#200000
1)
b1111111111111111111111111111111111111111111111111111111111011100 !
b1111111111111111111111111111111111111111111111111111111111011100 *
b110000 '
b1111111111111110000000000000000000000000000000000000000000000000 (
b11111111111111111111011100 #
b11111111111111111111011100 &
b101 $
b101 /
b100001000100000001000000011101000111010001000000101000001101111011100110110100101110100011010010111011001100101 0
b100100 .
b100100 -
#240000
0)
b1 !
b1 *
b0 '
b1 (
b100000 #
b100000 &
b11 "
b11 %
b110 $
b110 /
b100001000100000001000000011101000111010001000000100111001100101011001110110000101110100011010010111011001100101 0
b1111111111111111111111111111111111111111111111111111111111011100 .
b1111111111111111111111111111111111111111111111111111111111011100 -
#280000
1)
b1111111111111111111111111111111111111111111111111111111111011100 !
b1111111111111111111111111111111111111111111111111111111111011100 *
b110000 '
b1111111111011100000000000000000000000000000000000000000000000000 (
b11111111111111101110011111 #
b11111111111111101110011111 &
b111 $
b111 /
b100001101000010001000000011101000111010001000000101000001101111011100110110100101110100011010010111011001100101 0
b1 .
b1 -
#320000
0)
b1100111000110001 !
b1100111000110001 *
b0 '
b1100111000110001 (
b11100110011100011000101111 #
b11100110011100011000101111 &
b100 "
b100 %
b1000 $
b1000 /
b100001101000010001000000011101000111010001000000100111001100101011001110110000101110100011010010111011001100101 0
b1111111111111111111111111111111111111111111111111111111111011100 .
b1111111111111111111111111111111111111111111111111111111111011100 -
#360000
b11001110001100010000000000000000 !
b11001110001100010000000000000000 *
b11001110001100010000000000000000 (
b10000 '
b11101110011100011000101111 #
b11101110011100011000101111 &
b1001 $
b1001 /
b1001001010011010010000000111010001110100010000001010100011001010111001101110100001000000010001100110001001000000101101101100011011001010011001100110001001000000011110000111100001000000011000001011101 0
b1100111000110001 .
b1100111000110001 -
#400000
b110011100011000100000000000000000000000000000000 !
b110011100011000100000000000000000000000000000000 *
b110011100011000100000000000000000000000000000000 (
b100000 '
b11110110011100011000101111 #
b11110110011100011000101111 &
b1010 $
b1010 /
b100100101001101001000000011101000111010001000000101010001100101011100110111010000100000001000110011001000100000010110110110001101100101001100110011000100100000001111000011110000100000001100010011011001011101 0
b11001110001100010000000000000000 .
b11001110001100010000000000000000 -
#440000
b1100111000110001000000000000000000000000000000000000000000000000 !
b1100111000110001000000000000000000000000000000000000000000000000 *
b1100111000110001000000000000000000000000000000000000000000000000 (
b110000 '
b11111110011100011000101111 #
b11111110011100011000101111 &
b1011 $
b1011 /
b100100101001101001000000011101000111010001000000101010001100101011100110111010000100000001000110011001100100000010110110110001101100101001100110011000100100000001111000011110000100000001100110011001001011101 0
b110011100011000100000000000000000000000000000000 .
b110011100011000100000000000000000000000000000000 -
#480000
b101000001100 !
b101000001100 *
b0 '
b101000001100 (
b1000000010100000110001100 #
b1000000010100000110001100 &
b1100 $
b1100 /
b100100101001101001000000011101000111010001000000101010001100101011100110111010000100000001000110011010000100000010110110110001101100101001100110011000100100000001111000011110000100000001101000011100001011101 0
b1100111000110001000000000000000000000000000000000000000000000000 .
b1100111000110001000000000000000000000000000000000000000000000000 -
#520000
b1010000011000000000000000000 !
b1010000011000000000000000000 *
b1010000011000000000000000000 (
b10000 '
b1001000010100000110001100 #
b1001000010100000110001100 &
b1101 $
b1101 /
b10010010100110100100000001110100011101000100000010101000110010101110011011101000010000000100011001101010010000001011011011000010011000001100011001000000011110000111100001000000011000001011101 0
b101000001100 .
b101000001100 -
#560000
b10100000110000000000000000000000000000000000 !
b10100000110000000000000000000000000000000000 *
b10100000110000000000000000000000000000000000 (
b100000 '
b1010000010100000110001100 #
b1010000010100000110001100 &
b1110 $
b1110 /
b1001001010011010010000000111010001110100010000001010100011001010111001101110100001000000010001100110110001000000101101101100001001100000110001100100000001111000011110000100000001100010011011001011101 0
b1010000011000000000000000000 .
b1010000011000000000000000000 -
#600000
b101000001100000000000000000000000000000000000000000000000000 !
b101000001100000000000000000000000000000000000000000000000000 *
b101000001100000000000000000000000000000000000000000000000000 (
b110000 '
b1011000010100000110001100 #
b1011000010100000110001100 &
b1111 $
b1111 /
b1001001010011010010000000111010001110100010000001010100011001010111001101110100001000000010001100110111001000000101101101100001001100000110001100100000001111000011110000100000001100110011001001011101 0
b10100000110000000000000000000000000000000000 .
b10100000110000000000000000000000000000000000 -
#640000
b10111000111101 !
b10111000111101 *
b0 '
b10111000111101 (
b11000001011100011110111001 #
b11000001011100011110111001 &
b10000 $
b10000 /
b1001001010011010010000000111010001110100010000001010100011001010111001101110100001000000010001100111000001000000101101101100001001100000110001100100000001111000011110000100000001101000011100001011101 0
b101000001100000000000000000000000000000000000000000000000000 .
b101000001100000000000000000000000000000000000000000000000000 -
#680000
b101110001111010000000000000000 !
b101110001111010000000000000000 *
b101110001111010000000000000000 (
b10000 '
b11001001011100011110111001 #
b11001001011100011110111001 &
b10001 $
b10001 /
b1001001010011010010000000111010001110100010000001010100011001010111001101110100001000000010001100111001001000000101101100110010011001010011001101100100001000000011110000111100001000000011000001011101 0
b10111000111101 .
b10111000111101 -
#720000
b1011100011110100000000000000000000000000000000 !
b1011100011110100000000000000000000000000000000 *
b1011100011110100000000000000000000000000000000 (
b100000 '
b11010001011100011110111001 #
b11010001011100011110111001 &
b10010 $
b10010 /
b10010010100110100100000001110100011101000100000010101000110010101110011011101000010000000100011001100010011000000100000010110110011001001100101001100110110010000100000001111000011110000100000001100010011011001011101 0
b101110001111010000000000000000 .
b101110001111010000000000000000 -
#760000
b10111000111101000000000000000000000000000000000000000000000000 !
b10111000111101000000000000000000000000000000000000000000000000 *
b10111000111101000000000000000000000000000000000000000000000000 (
b110000 '
b11011001011100011110111001 #
b11011001011100011110111001 &
b10011 $
b10011 /
b10010010100110100100000001110100011101000100000010101000110010101110011011101000010000000100011001100010011000100100000010110110011001001100101001100110110010000100000001111000011110000100000001100110011001001011101 0
b1011100011110100000000000000000000000000000000 .
b1011100011110100000000000000000000000000000000 -
#800000
b10100 +
b10100 ,
b10100 $
b10100 /
b10010010100110100100000001110100011101000100000010101000110010101110011011101000010000000100011001100010011001000100000010110110011001001100101001100110110010000100000001111000011110000100000001101000011100001011101 0
b10111000111101000000000000000000000000000000000000000000000000 .
b10111000111101000000000000000000000000000000000000000000000000 -
