Lab07/SignExtender.v
module SignExtender(BusImm, Input, Ctrl); 
   output [63:0] BusImm; 
   input [25:0]  Input; 
   input [1:0]	 Ctrl; 
   
   wire 	 extBit;
   
   assign extBit =
		  (Ctrl == 2'b00) ? Input[21] : // I
		  (Ctrl == 2'b01) ? Input[20] : // D
		  (Ctrl == 2'b10) ? Input[25] : Input[23]; // B, else CB
 
   assign BusImm =
		  (Ctrl == 2'b00) ? {{52{extBit}}, Input[21:10]} : // I
		  (Ctrl == 2'b01) ? {{55{extBit}}, Input[20:12]} : // D
		  (Ctrl == 2'b10) ? {{38{extBit}}, Input} : {{45{extBit}}, Input[23:5]}; // B, else CB
   
endmodule

Lab07/SignExtenderTest.v
`timescale 1ns / 1ps

////////////////////////////////////////////////////////////////////////////////
// Company: 
// Engineer:
//
// Create Date:   10:02:47 03/05/2009
// Design Name:   ALU
// Module Name:   E:/350/Lab7/SignExtenderTest.v
// Project Name:  SignExtender
// Target Device:  
// Tool versions:  
// Description: 
//
// Verilog Test Fixture created by ISE for module: SignExtender
//
// Dependencies:
// 
// Revision:
// Revision 0.01 - File Created
// Additional Comments:
// 
////////////////////////////////////////////////////////////////////////////////

`define STRLEN 32
module SignExtenderTest_v;

   initial begin
      $dumpfile("SignExtenderTest.vcd");
      $dumpvars(0, SignExtenderTest_v);
   end
	task passTest;
		input [64:0] actualOut, expectedOut;
		input [`STRLEN*8:0] testType;
		inout [7:0] passed;
	
		if(actualOut == expectedOut) begin $display ("%s passed", testType); passed = passed + 1; end
		else $display ("%s failed: %x should be %x", testType, actualOut, expectedOut);
	endtask
	
	task allPassed;
		input [7:0] passed;
		input [7:0] numTests;
		
		if(passed == numTests) $display ("All tests passed");
		else $display("Some tests failed");
	endtask

	// Inputs
        reg [25:0]  Input;
        reg [1:0]  Ctrl;
	reg [7:0] passed;

	// Outputs
	wire [63:0] BusImm;

	// Instantiate the Unit Under Test (UUT)
	SignExtender uut (
		.BusImm(BusImm),
		.Input(Input),
		.Ctrl(Ctrl)
	);

	initial begin
		// Initialize Inputs
		Input = 0;
		Ctrl = 0;
		passed = 0;

                // Here is one example test vector, testing the ADD instruction:
		{Input, Ctrl} = {26'h24, 2'h0}; #40; passTest({BusImm}, 64'h24, "SE I-0", passed);
	        {Input, Ctrl} = {26'b11111111111111111111011100, 2'h0}; #40; passTest({BusImm}, 64'hffffffffffffffdc, "SE I-1", passed);
	        {Input, Ctrl} = {26'h24, 2'h1}; #40; passTest({BusImm}, 64'h24, "SE D-0", passed);
	        {Input, Ctrl} = {26'b11111111111111111111011100, 2'h1}; #40; passTest({BusImm}, 64'hffffffffffffffdc, "SE D-1", passed);
	        {Input, Ctrl} = {26'h24, 2'h2}; #40; passTest({BusImm}, 64'h24, "SE B-0", passed);
	        {Input, Ctrl} = {26'b11111111111111111111011100, 2'h2}; #40; passTest({BusImm}, 64'hffffffffffffffdc, "SE B-1", passed);
	        {Input, Ctrl} = {26'h24, 2'h3}; #40; passTest({BusImm}, 64'h24, "SE CB-0", passed);
	        {Input, Ctrl} = {26'b11111111111111111111011100, 2'h3}; #40; passTest({BusImm}, 64'hffffffffffffffdc, "SE CB-1", passed);
	        
		//Reformate and add your test vectors from the prelab here following the example of the testvector above.	


		allPassed(passed, 8);
	end
      
endmodule

Lab07/SignExtenderTest.vcd
$date
	Wed Oct 26 20:32:23 2022
$end
$version
	Icarus Verilog
$end
$timescale
	1ps
$end
$scope module SignExtenderTest_v $end
$var wire 64 ! BusImm [63:0] $end
$var reg 2 " Ctrl [1:0] $end
$var reg 26 # Input [25:0] $end
$var reg 8 $ passed [7:0] $end
$scope module uut $end
$var wire 2 % Ctrl [1:0] $end
$var wire 26 & Input [25:0] $end
$var wire 1 ' extBit $end
$var wire 64 ( BusImm [63:0] $end
$upscope $end
$scope task allPassed $end
$var reg 8 ) numTests [7:0] $end
$var reg 8 * passed [7:0] $end
$upscope $end
$scope task passTest $end
$var reg 65 + actualOut [64:0] $end
$var reg 65 , expectedOut [64:0] $end
$var reg 8 - passed [7:0] $end
$var reg 257 . testType [256:0] $end
$upscope $end
$upscope $end
$enddefinitions $end
#0
$dumpvars
bx .
bx -
bx ,
bx +
bx *
bx )
b0 (
0'
b100100 &
b0 %
b0 $
b100100 #
b0 "
b0 !
$end
#40000
1'
b1111111111111111111111111111111111111111111111111111111111111111 !
b1111111111111111111111111111111111111111111111111111111111111111 (
b11111111111111111111011100 #
b11111111111111111111011100 &
b0 -
b10100110100010100100000010010010010110100110000 .
b100100 ,
b0 +
#80000
0'
b0 !
b0 (
b100100 #
b100100 &
b1 "
b1 %
b10100110100010100100000010010010010110100110001 .
b1111111111111111111111111111111111111111111111111111111111011100 ,
b1111111111111111111111111111111111111111111111111111111111111111 +
#120000
1'
b1111111111111111111111111111111111111111111111111111111111111111 !
b1111111111111111111111111111111111111111111111111111111111111111 (
b11111111111111111111011100 #
b11111111111111111111011100 &
b10100110100010100100000010001000010110100110000 .
b100100 ,
b0 +
#160000
0'
b100100 !
b100100 (
b100100 #
b100100 &
b10 "
b10 %
b10100110100010100100000010001000010110100110001 .
b1111111111111111111111111111111111111111111111111111111111011100 ,
b1111111111111111111111111111111111111111111111111111111111111111 +
#200000
1'
b1111111111111111111111111111111111111111111111111111111111011100 !
b1111111111111111111111111111111111111111111111111111111111011100 (
b11111111111111111111011100 #
b11111111111111111111011100 &
b1 $
b1 -
b10100110100010100100000010000100010110100110000 .
b100100 ,
b100100 +
#240000
0'
b1 !
b1 (
b100100 #
b100100 &
b11 "
b11 %
b10 $
b10 -
b10100110100010100100000010000100010110100110001 .
b1111111111111111111111111111111111111111111111111111111111011100 ,
b1111111111111111111111111111111111111111111111111111111111011100 +
#280000
1'
b1111111111111111111111111111111111111111111111111111111111111110 !
b1111111111111111111111111111111111111111111111111111111111111110 (
b11111111111111111111011100 #
b11111111111111111111011100 &
b1010011010001010010000001000011010000100010110100110000 .
b100100 ,
b1 +
#320000
b1000 )
b10 *
b1010011010001010010000001000011010000100010110100110001 .
b1111111111111111111111111111111111111111111111111111111111011100 ,
b1111111111111111111111111111111111111111111111111111111111111110 +
