Lab07/SignExtender.v
`define I    2'b00
`define D    2'b01
`define B    2'b10
`define CB   2'b11

module SignExtender(BusImm, Input, Ctrl); 
   output [63:0] BusImm; 
   input [25:0]  Input; 
   input [1:0]	 Ctrl; 
   
   wire 	 extBit;

   // Passed Tests
   assign extBit =
		  (Ctrl == `I) ? Input[21] : // I
		  (Ctrl == `D) ? Input[20] : // D
		  (Ctrl == `B) ? Input[25] : // B
                      Input[23];             // CB

   
   assign BusImm =
		  (Ctrl == `I) ? {{52{extBit}}, Input[21:10]} : // I
		  (Ctrl == `D) ? {{55{extBit}}, Input[20:12]} : // D
		  (Ctrl == `B) ? {{38{extBit}}, Input} :        // B
		      {{45{extBit}}, Input[23:5]};              // CB
   
endmodule

Lab07/SignExtenderTest.v
`timescale 1ns / 1ps

////////////////////////////////////////////////////////////////////////////////
// Company: 
// Engineer:
//
// Create Date:   10:02:47 03/05/2009
// Design Name:   ALU
// Module Name:   E:/350/Lab7/SignExtenderTest.v
// Project Name:  SignExtender
// Target Device:  
// Tool versions:  
// Description: 
//
// Verilog Test Fixture created by ISE for module: SignExtender
//$display ("%s passed", testType)
// Dependencies:
// 
// Revision:
// Revision 0.01 - File Created
// Additional Comments:
// 
////////////////////////////////////////////////////////////////////////////////

`define STRLEN 32
module SignExtenderTest_v;

   initial begin
      $dumpfile("SignExtenderTest.vcd");
      $dumpvars(0, SignExtenderTest_v);
   end
	task passTest;
		input [63:0] actualOut, expectedOut;
		input [`STRLEN*8:0] testType;
		inout [7:0] passed;
	
		if(actualOut == expectedOut) begin $display ("%s passed", testType); passed = passed + 1; end
		else $display ("%s failed: %x should be %x", testType, actualOut, expectedOut);
	endtask
	
	task allPassed;
		input [7:0] passed;
		input [7:0] numTests;
		
		if(passed == numTests) $display ("All tests passed");
		else $display("Some tests failed");
	endtask

	// Inputs
        reg [25:0]  Input;
        reg [1:0]  Ctrl;
	reg [7:0] passed;

	// Outputs
	wire [63:0] BusImm;

	// Instantiate the Unit Under Test (UUT)
	SignExtender uut (
		.BusImm(BusImm),
		.Input(Input),
		.Ctrl(Ctrl)
	);

	initial begin
		// Initialize Inputs
		Input = 0;
		Ctrl = 0;
		passed = 0;

                // Here is one example test vector, testing the ADD instruction:
	        $display ("8 Test Vectors:");
		{Input, Ctrl} = {26'h444, 2'h0}; #40; passTest({BusImm}, 64'h1, "I  :: Positive", passed);
	        {Input, Ctrl} = {26'hfff73ff, 2'h0}; #40; passTest({BusImm}, 64'hffffffffffffffdc, "I  :: Negative", passed);
	        {Input, Ctrl} = {26'h1234, 2'h1}; #40; passTest({BusImm}, 64'h1, "D  :: Positive", passed);
	        {Input, Ctrl} = {26'hffdcfff, 2'h1}; #40; passTest({BusImm}, 64'hffffffffffffffdc, "D  :: Negative", passed);
	        {Input, Ctrl} = {26'h24, 2'h2}; #40; passTest({BusImm}, 64'h24, "B  :: Positive", passed);
	        {Input, Ctrl} = {26'hfffffdc, 2'h2}; #40; passTest({BusImm}, 64'hffffffffffffffdc, "B  :: Negative", passed);
	        {Input, Ctrl} = {26'h20, 2'h3}; #40; passTest({BusImm}, 64'h1, "CB :: Positive", passed);
	        {Input, Ctrl} = {26'hffffb9f, 2'h3}; #40; passTest({BusImm}, 64'hffffffffffffffdc, "CB :: Negative", passed);
	        
		//Reformate and add your test vectors from the prelab here following the example of the testvector above.	


		allPassed(passed, 8);
	end
      
endmodule

Lab07/SignExtenderTest.vcd
$date
	Wed Nov  2 17:44:50 2022
$end
$version
	Icarus Verilog
$end
$timescale
	1ps
$end
$scope module SignExtenderTest_v $end
$var wire 64 ! BusImm [63:0] $end
$var reg 2 " Ctrl [1:0] $end
$var reg 26 # Input [25:0] $end
$var reg 8 $ passed [7:0] $end
$scope module uut $end
$var wire 2 % Ctrl [1:0] $end
$var wire 26 & Input [25:0] $end
$var wire 1 ' extBit $end
$var wire 64 ( BusImm [63:0] $end
$upscope $end
$scope task allPassed $end
$var reg 8 ) numTests [7:0] $end
$var reg 8 * passed [7:0] $end
$upscope $end
$scope task passTest $end
$var reg 64 + actualOut [63:0] $end
$var reg 64 , expectedOut [63:0] $end
$var reg 8 - passed [7:0] $end
$var reg 257 . testType [256:0] $end
$upscope $end
$upscope $end
$enddefinitions $end
#0
$dumpvars
bx .
bx -
bx ,
bx +
bx *
bx )
b1 (
0'
b10001000100 &
b0 %
b0 $
b10001000100 #
b0 "
b1 !
$end
#40000
1'
b1111111111111111111111111111111111111111111111111111111111011100 !
b1111111111111111111111111111111111111111111111111111111111011100 (
b11111111110111001111111111 #
b11111111110111001111111111 &
b1 $
b1 -
b100100100100000001000000011101000111010001000000101000001101111011100110110100101110100011010010111011001100101 .
b1 ,
b1 +
#80000
0'
b1 !
b1 (
b1001000110100 #
b1001000110100 &
b1 "
b1 %
b10 $
b10 -
b100100100100000001000000011101000111010001000000100111001100101011001110110000101110100011010010111011001100101 .
b1111111111111111111111111111111111111111111111111111111111011100 ,
b1111111111111111111111111111111111111111111111111111111111011100 +
#120000
1'
b1111111111111111111111111111111111111111111111111111111111011100 !
b1111111111111111111111111111111111111111111111111111111111011100 (
b11111111011100111111111111 #
b11111111011100111111111111 &
b11 $
b11 -
b100010000100000001000000011101000111010001000000101000001101111011100110110100101110100011010010111011001100101 .
b1 ,
b1 +
#160000
0'
b100100 !
b100100 (
b100100 #
b100100 &
b10 "
b10 %
b100 $
b100 -
b100010000100000001000000011101000111010001000000100111001100101011001110110000101110100011010010111011001100101 .
b1111111111111111111111111111111111111111111111111111111111011100 ,
b1111111111111111111111111111111111111111111111111111111111011100 +
#200000
1'
b1111111111111111111111111111111111111111111111111111111111011100 !
b1111111111111111111111111111111111111111111111111111111111011100 (
b11111111111111111111011100 #
b11111111111111111111011100 &
b101 $
b101 -
b100001000100000001000000011101000111010001000000101000001101111011100110110100101110100011010010111011001100101 .
b100100 ,
b100100 +
#240000
0'
b1 !
b1 (
b100000 #
b100000 &
b11 "
b11 %
b110 $
b110 -
b100001000100000001000000011101000111010001000000100111001100101011001110110000101110100011010010111011001100101 .
b1111111111111111111111111111111111111111111111111111111111011100 ,
b1111111111111111111111111111111111111111111111111111111111011100 +
#280000
1'
b1111111111111111111111111111111111111111111111111111111111011100 !
b1111111111111111111111111111111111111111111111111111111111011100 (
b11111111111111101110011111 #
b11111111111111101110011111 &
b111 $
b111 -
b100001101000010001000000011101000111010001000000101000001101111011100110110100101110100011010010111011001100101 .
b1 ,
b1 +
#320000
b1000 )
b1000 *
b1000 $
b1000 -
b100001101000010001000000011101000111010001000000100111001100101011001110110000101110100011010010111011001100101 .
b1111111111111111111111111111111111111111111111111111111111011100 ,
b1111111111111111111111111111111111111111111111111111111111011100 +
