Lab08/NextPClogic.v
////////////////////////////////////////////////////////////////////////////////
//                                                                            //
//                                                                            //
// VARS:                                                                      //
//     - SignExtImm64 = Output of sign extender                               //
//     - CurrentPC    = Current program counter                               //
//     - Branch       = `true` if instruction type B                          //
//     - Uncondbranch = `true` if instruction type CB                         //
//     - ALUZero      = ALU "zero" output                                     //
//                                                                            //
//                                                                            //
////////////////////////////////////////////////////////////////////////////////


module NextPClogic(NextPC, CurrentPC, SignExtImm64, Branch, ALUZero, Uncondbranch); 
   input [63:0] CurrentPC, SignExtImm64; 
   input 	Branch, ALUZero, Uncondbranch; 
   output [63:0] NextPC; 

   /* write your code here */
   wire 	 sel = ((ALUZero & Branch) | Uncondbranch);

   // Might have to put `CurrentPC` inside ternary operator result
   assign NextPC = CurrentPC + (sel ? (SignExtImm64<<2) : (3'b100));

endmodule

Lab08/NextPClogicTest.v
`timescale 1ns / 1ps

////////////////////////////////////////////////////////////////////////////////
// Company: 
// Engineer:
//
// Create Date:   11/09/2022
// Design Name:   NextPClogic
// Module Name:   E:/350/Lab8/NextPClogic.v
// Project Name:  NextPClogic
// Target Device:  
// Tool versions:  
// Description: 
//
// Verilog Test Fixture created by ISE for module: NextPClogic
//
// Dependencies:
// 
// Revision:
// Revision 0.01 - File Created
// Additional Comments:
// 
////////////////////////////////////////////////////////////////////////////////

`define STRLEN 16 // was 32
module NextPClogicTest_v;

   initial begin
      $dumpfile("NextPClogicTest.vcd");
      $dumpvars(0, NextPClogicTest_v);
   end

	task passTest;
	   input [63:0] expectOut, actualOut;
	   input [`STRLEN*8:0] testType;
	   inout [7:0] passed;

	       if (actualOut == expectOut) begin
                  $display("\n\n%s :: Passed\n\tCurrPC\t= %x\n\tSEImm64\t= %x\n\tBranch\t= %x\n\tALUZero\t= %x\n\tUnCondB\t= %x\n\tNextPC\t= %x", testType, CurrentPC, SignExtImm64, Branch, ALUZero, Uncondbranch, actualOut);
		  passed = passed + 1;
	       end
	       else $display("\n\n%s :: Failed\n\tCurrPC\t= %x\n\tSEImm64\t= %x\n\tBranch\t= %x\n\tALUZero\t= %x\n\tUnCondB\t= %x\n\tNextPC\t= %x\tShould be: %x", testType, CurrentPC, SignExtImm64, Branch, ALUZero, Uncondbranch, actualOut, expectOut);
	endtask
	
	task allPassed;
		input [7:0] passed;
		input [7:0] numTests;
		
		if(passed == numTests) $display ("All tests passed");
		else $display("Some tests failed");
	endtask

   // Inputs
   reg [63:0] 		    CurrentPC;
   reg [63:0] 		    SignExtImm64;
   reg 			    Branch, ALUZero, Uncondbranch;
   reg [7:0] 		    passed;
   
   // Outputs
   wire [63:0] 		    NextPC;

   // Instantiate the Unit Under Test (UUT)
   NextPClogic uut (
		    .NextPC(NextPC),
		    .CurrentPC(CurrentPC),
		    .SignExtImm64(SignExtImm64),
		    .Branch(Branch),
		    .ALUZero(ALUZero),
		    .Uncondbranch(Uncondbranch)
		    );

   initial begin
      // Initialize Inputs
      CurrentPC = 0;
      SignExtImm64 = 0;
      Branch = 0;
      ALUZero = 0;
      Uncondbranch = 0;
      passed = 0;
      
      // TEST VECTORS:
      $display ("8 Test Vectors:");
      // Test 1
      {CurrentPC, SignExtImm64, Branch, ALUZero, Uncondbranch} = {64'h30, 64'h4, 1'b1, 1'b1, 1'b0}; #40; 
      passTest(64'h40, {NextPC}, "1) CBZ+ True", passed);
      
      // Test 2
      {CurrentPC, SignExtImm64, Branch, ALUZero, Uncondbranch} = {64'h30, 64'h4, 1'b1, 1'b0, 1'b0}; #40;
      passTest(64'h34, {NextPC}, "2) CBZ+ False", passed);
      
      // Test 3
      {CurrentPC, SignExtImm64, Branch, ALUZero, Uncondbranch} = {64'h30, -64'h4, 1'b1, 1'b1, 1'b0}; #40;
      passTest(64'h20, {NextPC}, "3) CBZ- True", passed);
      
      // Test 4
      {CurrentPC, SignExtImm64, Branch, ALUZero, Uncondbranch} = {64'h30, -64'h4, 1'b1, 1'b0, 1'b0}; #40;
      passTest(64'h34, {NextPC}, "4) CBZ- False", passed);
      
      // Test 5
      {CurrentPC, SignExtImm64, Branch, ALUZero, Uncondbranch} = {64'h30, 64'h4, 1'b0, 1'b1, 1'b1}; #40;
      passTest(64'h40, {NextPC}, "5) B+ True", passed);
      
      // Test 6
      {CurrentPC, SignExtImm64, Branch, ALUZero, Uncondbranch} = {64'h30, 64'h4, 1'b0, 1'b0, 1'b1}; #40;
      passTest(64'h40, {NextPC}, "6) B+ False", passed);
      
      // Test 7
      {CurrentPC, SignExtImm64, Branch, ALUZero, Uncondbranch} = {64'h30, -64'h4, 1'b0, 1'b1, 1'b1}; #40;
      passTest(64'h20, {NextPC}, "7) B- True", passed);
      
      // Test 8
      {CurrentPC, SignExtImm64, Branch, ALUZero, Uncondbranch} = {64'h30, -64'h4, 1'b0, 1'b0, 1'b1}; #40;
      passTest(64'h20, {NextPC}, "8) B- False", passed);
      // Should be 8 tests total      
      
      allPassed(passed, 8);
   end   
endmodule

Lab08/NextPClogicTest.vcd
$date
	Tue Nov 15 18:36:28 2022
$end
$version
	Icarus Verilog
$end
$timescale
	1ps
$end
$scope module NextPClogicTest_v $end
$var wire 64 ! NextPC [63:0] $end
$var reg 1 " ALUZero $end
$var reg 1 # Branch $end
$var reg 64 $ CurrentPC [63:0] $end
$var reg 64 % SignExtImm64 [63:0] $end
$var reg 1 & Uncondbranch $end
$var reg 8 ' passed [7:0] $end
$scope module uut $end
$var wire 1 " ALUZero $end
$var wire 1 # Branch $end
$var wire 64 ( CurrentPC [63:0] $end
$var wire 64 ) SignExtImm64 [63:0] $end
$var wire 1 & Uncondbranch $end
$var wire 1 * sel $end
$var wire 64 + NextPC [63:0] $end
$upscope $end
$scope task allPassed $end
$var reg 8 , numTests [7:0] $end
$var reg 8 - passed [7:0] $end
$upscope $end
$scope task passTest $end
$var reg 64 . actualOut [63:0] $end
$var reg 64 / expectOut [63:0] $end
$var reg 8 0 passed [7:0] $end
$var reg 129 1 testType [128:0] $end
$upscope $end
$upscope $end
$enddefinitions $end
#0
$dumpvars
bx 1
bx 0
bx /
bx .
bx -
bx ,
b1000000 +
1*
b100 )
b110000 (
b0 '
0&
b100 %
b110000 $
1#
1"
b1000000 !
$end
#40000
b110100 !
b110100 +
0*
0"
b1 '
b1 0
b1100010010100100100000010000110100001001011010001010110010000001010100011100100111010101100101 1
b1000000 .
b1000000 /
#80000
b100000 !
b100000 +
1*
b1111111111111111111111111111111111111111111111111111111111111100 %
b1111111111111111111111111111111111111111111111111111111111111100 )
1"
b10 '
b10 0
b110010001010010010000001000011010000100101101000101011001000000100011001100001011011000111001101100101 1
b110100 .
b110100 /
#120000
b110100 !
b110100 +
0*
0"
b11 '
b11 0
b1100110010100100100000010000110100001001011010001011010010000001010100011100100111010101100101 1
b100000 .
b100000 /
#160000
b1000000 !
b1000000 +
1*
b100 %
b100 )
0#
1"
1&
b100 '
b100 0
b110100001010010010000001000011010000100101101000101101001000000100011001100001011011000111001101100101 1
b110100 .
b110100 /
#200000
0"
b101 '
b101 0
b110101001010010010000001000010001010110010000001010100011100100111010101100101 1
b1000000 .
b1000000 /
#240000
b100000 !
b100000 +
b1111111111111111111111111111111111111111111111111111111111111100 %
b1111111111111111111111111111111111111111111111111111111111111100 )
1"
b110 '
b110 0
b11011000101001001000000100001000101011001000000100011001100001011011000111001101100101 1
#280000
0"
b111 '
b111 0
b110111001010010010000001000010001011010010000001010100011100100111010101100101 1
b100000 .
b100000 /
#320000
b1000 ,
b1000 -
b1000 '
b1000 0
b11100000101001001000000100001000101101001000000100011001100001011011000111001101100101 1
