Lab08/RegisterFile.v
module RegisterFile(BusA, BusB, BusW, RA, RB, RW, RegWr, Clk);
   output [63:0] BusA;   
   output [63:0] BusB;
   input [63:0]  BusW;
   input [4:0] 	 RA, RB, RW;
   input 	 RegWr;
   input 	 Clk;
   reg [63:0] 	 registers [31:0]; // 32 registers, each 64 bits
     
   assign #2 BusA = ((RA == 31) ? 64'h0 : registers[RA]);
   assign #2 BusB = ((RB == 31) ? 64'h0 : registers[RB]);
     
   always @ (negedge Clk) begin
      if(RegWr)
        registers[RW] <= #3 BusW;
   end
endmodule

Lab08/RegisterFileTest.v
`timescale 1ns / 1ps

////////////////////////////////////////////////////////////////////////////////
// Company: 
// Engineer:
//
// Create Date:   10:13:28 03/03/2009
// Design Name:   RegisterFile
// Module Name:   E:/350/Lab7/RegisterFile/RegisterFileTest.v
// Project Name:  RegisterFile
// Target Device:  
// Tool versions:  
// Description: 
//
// Verilog Test Fixture created by ISE for module: RegisterFile
//
// Dependencies:
// 
// Revision:
// Revision 0.01 - File Created
// Additional Comments:
// 
////////////////////////////////////////////////////////////////////////////////

`define STRLEN 32
module RegisterFileTest_v;

   initial begin
      $dumpfile("RegisterFileTest.vcd");
      $dumpvars(0, RegisterFileTest_v);
   end

   task passTest;
      input [63:0] actualOut, expectedOut;
      input [`STRLEN*8:0] testType;
      inout [7:0] 	  passed;
      
      if(actualOut == expectedOut) begin $display ("%s passed", testType); passed = passed + 1; end
      else $display ("%s failed: %d should be %d", testType, actualOut, expectedOut);
   endtask
   
   task allPassed;
      input [7:0] passed;
      input [7:0] numTests;
      
      if(passed == numTests) $display ("All tests passed");
      else $display("Some tests failed");
   endtask

   // Inputs
   reg [63:0] 	  BusW;
   reg [4:0] 	  RA;
   reg [4:0] 	  RB;
   reg [4:0] 	  RW;
   reg 		  RegWr;
   reg 		  Clk;
   reg [7:0] 	  passed;

   // Outputs
   wire [63:0] 	  BusA;
   wire [63:0] 	  BusB;

   // Instantiate the Unit Under Test (UUT)
   RegisterFile uut (
		     .BusA(BusA), 
		     .BusB(BusB), 
		     .BusW(BusW), 
		     .RA(RA), 
		     .RB(RB), 
		     .RW(RW), 
		     .RegWr(RegWr), 
		     .Clk(Clk)
		     );

   initial begin
      // Initialize Inputs
      BusW = 0;
      RA = 0;
      RB = 0;
      RW = 0;
      RegWr = 0;
      Clk = 1;
      passed = 0;
      
      #10;

      // Add stimulus here
      {RA, RB, RW, BusW, RegWr} = {5'd31, 5'd31, 5'd31, 64'h0, 1'b0};
      #10
	passTest(BusA, 64'd0, "Initial $0 Check 1", passed);
      passTest(BusB, 64'd0, "Initial $0 Check 2", passed);
      #10; Clk = 0; #10; Clk = 1;
      
      {RA, RB, RW, BusW, RegWr} = {5'd31, 5'd31, 5'd31, 64'h12345678, 1'b1};
      passTest(BusA, 64'd0, "Initial $0 Check 3", passed);
      passTest(BusB, 64'd0, "Initial $0 Check 4", passed);
      #10; Clk = 0; #10; Clk = 1;
      passTest(BusA, 64'd0, "$0 Stays 0 Check 1", passed);
      passTest(BusB, 64'd0, "$0 Stays 0 Check 2", passed);

      // This segment clears all registers
      {RA, RB, RW, BusW, RegWr} = {5'd0, 5'd0, 5'd0, 64'h0, 1'b1};#10; Clk = 0; #10; Clk = 1;
      {RA, RB, RW, BusW, RegWr} = {5'd0, 5'd0, 5'd1, 64'h1, 1'b1};#10; Clk = 0; #10; Clk = 1;
      {RA, RB, RW, BusW, RegWr} = {5'd0, 5'd0, 5'd2, 64'h2, 1'b1};#10; Clk = 0; #10; Clk = 1;
      {RA, RB, RW, BusW, RegWr} = {5'd0, 5'd0, 5'd3, 64'h3, 1'b1};#10; Clk = 0; #10; Clk = 1;
      {RA, RB, RW, BusW, RegWr} = {5'd0, 5'd0, 5'd4, 64'h4, 1'b1};#10; Clk = 0; #10; Clk = 1;
      {RA, RB, RW, BusW, RegWr} = {5'd0, 5'd0, 5'd5, 64'h5, 1'b1};#10; Clk = 0; #10; Clk = 1;
      {RA, RB, RW, BusW, RegWr} = {5'd0, 5'd0, 5'd6, 64'h6, 1'b1};#10; Clk = 0; #10; Clk = 1;
      {RA, RB, RW, BusW, RegWr} = {5'd0, 5'd0, 5'd7, 64'h7, 1'b1};#10; Clk = 0; #10; Clk = 1;
      {RA, RB, RW, BusW, RegWr} = {5'd0, 5'd0, 5'd8, 64'h8, 1'b1};#10; Clk = 0; #10; Clk = 1;
      {RA, RB, RW, BusW, RegWr} = {5'd0, 5'd0, 5'd9, 64'h9, 1'b1};#10; Clk = 0; #10; Clk = 1;
      {RA, RB, RW, BusW, RegWr} = {5'd0, 5'd0, 5'd10, 64'd10, 1'b1};#10; Clk = 0; #10; Clk = 1;
      {RA, RB, RW, BusW, RegWr} = {5'd0, 5'd0, 5'd11, 64'd11, 1'b1};#10; Clk = 0; #10; Clk = 1;
      {RA, RB, RW, BusW, RegWr} = {5'd0, 5'd0, 5'd12, 64'd12, 1'b1};#10; Clk = 0; #10; Clk = 1;
      {RA, RB, RW, BusW, RegWr} = {5'd0, 5'd0, 5'd13, 64'd13, 1'b1};#10; Clk = 0; #10; Clk = 1;
      {RA, RB, RW, BusW, RegWr} = {5'd0, 5'd0, 5'd14, 64'd14, 1'b1};#10; Clk = 0; #10; Clk = 1;
      {RA, RB, RW, BusW, RegWr} = {5'd0, 5'd0, 5'd15, 64'd15, 1'b1};#10; Clk = 0; #10; Clk = 1;
      {RA, RB, RW, BusW, RegWr} = {5'd0, 5'd0, 5'd16, 64'd16, 1'b1};#10; Clk = 0; #10; Clk = 1;
      {RA, RB, RW, BusW, RegWr} = {5'd0, 5'd0, 5'd17, 64'd17, 1'b1};#10; Clk = 0; #10; Clk = 1;
      {RA, RB, RW, BusW, RegWr} = {5'd0, 5'd0, 5'd18, 64'd18, 1'b1};#10; Clk = 0; #10; Clk = 1;
      {RA, RB, RW, BusW, RegWr} = {5'd0, 5'd0, 5'd19, 64'd19, 1'b1};#10; Clk = 0; #10; Clk = 1;
      {RA, RB, RW, BusW, RegWr} = {5'd0, 5'd0, 5'd20, 64'd20, 1'b1};#10; Clk = 0; #10; Clk = 1;
      {RA, RB, RW, BusW, RegWr} = {5'd0, 5'd0, 5'd21, 64'd21, 1'b1};#10; Clk = 0; #10; Clk = 1;
      {RA, RB, RW, BusW, RegWr} = {5'd0, 5'd0, 5'd22, 64'd22, 1'b1};#10; Clk = 0; #10; Clk = 1;
      {RA, RB, RW, BusW, RegWr} = {5'd0, 5'd0, 5'd23, 64'd23, 1'b1};#10; Clk = 0; #10; Clk = 1;
      {RA, RB, RW, BusW, RegWr} = {5'd0, 5'd0, 5'd24, 64'd24, 1'b1};#10; Clk = 0; #10; Clk = 1;
      {RA, RB, RW, BusW, RegWr} = {5'd0, 5'd0, 5'd25, 64'd25, 1'b1};#10; Clk = 0; #10; Clk = 1;
      {RA, RB, RW, BusW, RegWr} = {5'd0, 5'd0, 5'd26, 64'd26, 1'b1};#10; Clk = 0; #10; Clk = 1;
      {RA, RB, RW, BusW, RegWr} = {5'd0, 5'd0, 5'd27, 64'd27, 1'b1};#10; Clk = 0; #10; Clk = 1;
      {RA, RB, RW, BusW, RegWr} = {5'd0, 5'd0, 5'd28, 64'd28, 1'b1};#10; Clk = 0; #10; Clk = 1;
      {RA, RB, RW, BusW, RegWr} = {5'd0, 5'd0, 5'd29, 64'd29, 1'b1};#10; Clk = 0; #10; Clk = 1;
      {RA, RB, RW, BusW, RegWr} = {5'd0, 5'd0, 5'd30, 64'd30, 1'b1};#10; Clk = 0; #10; Clk = 1;
      {RA, RB, RW, BusW, RegWr} = {5'd0, 5'd0, 5'd31, 64'd31, 1'b1};#10; Clk = 0; #10; Clk = 1;

      {RA, RB, RW, BusW, RegWr} = {5'd1, 5'd2, 5'd1, 64'h12345678, 1'b1};
      #4;
      passTest(BusA, 64'd1, "Initial Value Check 1", passed);
      passTest(BusB, 64'd2, "Initial Value Check 2", passed);
      #6; Clk = 0; #10; Clk = 1;
      passTest(BusA, 64'h12345678, "Value Updated 1", passed);
      passTest(BusB, 64'd2, "Value Stayed Same 1", passed);

      {RA, RB, RW, BusW, RegWr} = {5'd3, 5'd4, 5'd3, 64'h12345678, 1'b0};
      #4;
      passTest(BusA, 64'd3, "Initial Value Check 3", passed);
      passTest(BusB, 64'd4, "Initial Value Check 4", passed);
      #6; Clk = 0; #10; Clk = 1;
      passTest(BusA, 64'd3, "Value Not Updated 2", passed);
      passTest(BusB, 64'd4, "Value Stayed Same 2", passed);
      
      {RA, RB, RW, BusW, RegWr} = {5'd5, 5'd6, 5'd3, 64'h12345678, 1'b0};
      #4;
      passTest(BusA, 64'd5, "Initial Value Check 5", passed);
      passTest(BusB, 64'd6, "Initial Value Check 6", passed);
      #6; Clk = 0; #10; Clk = 1;
      passTest(BusA, 64'd5, "Value Not Updated 3", passed);
      passTest(BusB, 64'd6, "Value Stayed Same 3", passed);
      
      {RA, RB, RW, BusW, RegWr} = {5'd7, 5'd8, 5'd3, 64'h12345678, 1'b0};
      #4;
      passTest(BusA, 64'd7, "Initial Value Check 7", passed);
      passTest(BusB, 64'd8, "Initial Value Check 8", passed);
      #6; Clk = 0; #10; Clk = 1;
      passTest(BusA, 64'd7, "Value Not Updated 4", passed);
      passTest(BusB, 64'd8, "Value Stayed Same 4", passed);
      
      {RA, RB, RW, BusW, RegWr} = {5'd9, 5'd10, 5'd3, 64'h12345678, 1'b0};
      #4;
      passTest(BusA, 64'd9, "Initial Value Check 9", passed);
      passTest(BusB, 64'd10, "Initial Value Check 10", passed);
      #6; Clk = 0; #10; Clk = 1;
      passTest(BusA, 64'd9, "Value Not Updated 5", passed);
      passTest(BusB, 64'd10, "Value Stayed Same 5", passed);

      {RA, RB, RW, BusW, RegWr} = {5'd11, 5'd12, 5'd3, 64'h12345678, 1'b0};
      #4;
      passTest(BusA, 64'd11, "Initial Value Check 11", passed);
      passTest(BusB, 64'd12, "Initial Value Check 12", passed);
      #6; Clk = 0; #10; Clk = 1;
      passTest(BusA, 64'd11, "Value Not Updated 6", passed);
      passTest(BusB, 64'd12, "Value Stayed Same 6", passed);

      {RA, RB, RW, BusW, RegWr} = {5'd13, 5'd14, 5'd3, 64'h12345678, 1'b0};
      #4;
      passTest(BusA, 64'd13, "Initial Value Check 13", passed);
      passTest(BusB, 64'd14, "Initial Value Check 14", passed);
      #6; Clk = 0; #10; Clk = 1;
      passTest(BusA, 64'd13, "Value Not Updated 7", passed);
      passTest(BusB, 64'd14, "Value Stayed Same 7", passed);

      {RA, RB, RW, BusW, RegWr} = {5'd15, 5'd16, 5'd3, 64'h12345678, 1'b0};
      #4;
      passTest(BusA, 64'd15, "Initial Value Check 15", passed);
      passTest(BusB, 64'd16, "Initial Value Check 16", passed);
      #6; Clk = 0; #10; Clk = 1;
      passTest(BusA, 64'd15, "Value Not Updated 8", passed);
      passTest(BusB, 64'd16, "Value Stayed Same 8", passed);

      {RA, RB, RW, BusW, RegWr} = {5'd17, 5'd18, 5'd3, 64'h12345678, 1'b0};
      #4;
      passTest(BusA, 64'd17, "Initial Value Check 17", passed);
      passTest(BusB, 64'd18, "Initial Value Check 18", passed);
      #6; Clk = 0; #10; Clk = 1;
      passTest(BusA, 64'd17, "Value Not Updated 9", passed);
      passTest(BusB, 64'd18, "Value Stayed Same 9", passed);

      {RA, RB, RW, BusW, RegWr} = {5'd19, 5'd20, 5'd3, 64'h12345678, 1'b0};
      #4;
      passTest(BusA, 64'd19, "Initial Value Check 19", passed);
      passTest(BusB, 64'd20, "Initial Value Check 20", passed);
      #6; Clk = 0; #10; Clk = 1;
      passTest(BusA, 64'd19, "Value Not Updated 10", passed);
      passTest(BusB, 64'd20, "Value Stayed Same 10", passed);

      {RA, RB, RW, BusW, RegWr} = {5'd21, 5'd22, 5'd3, 64'h12345678, 1'b0};
      #4;
      passTest(BusA, 64'd21, "Initial Value Check 21", passed);
      passTest(BusB, 64'd22, "Initial Value Check 22", passed);
      #6; Clk = 0; #10; Clk = 1;
      passTest(BusA, 64'd21, "Value Not Updated 11", passed);
      passTest(BusB, 64'd22, "Value Stayed Same 11", passed);

      {RA, RB, RW, BusW, RegWr} = {5'd23, 5'd24, 5'd3, 64'h12345678, 1'b0};
      #4;
      passTest(BusA, 64'd23, "Initial Value Check 23", passed);
      passTest(BusB, 64'd24, "Initial Value Check 24", passed);
      #6; Clk = 0; #10; Clk = 1;
      passTest(BusA, 64'd23, "Value Not Updated 12", passed);
      passTest(BusB, 64'd24, "Value Stayed Same 12", passed);

      {RA, RB, RW, BusW, RegWr} = {5'd25, 5'd26, 5'd3, 64'h12345678, 1'b0};
      #4;
      passTest(BusA, 64'd25, "Initial Value Check 25", passed);
      passTest(BusB, 64'd26, "Initial Value Check 26", passed);
      #6; Clk = 0; #10; Clk = 1;
      passTest(BusA, 64'd25, "Value Not Updated 13", passed);
      passTest(BusB, 64'd26, "Value Stayed Same 13", passed);

      {RA, RB, RW, BusW, RegWr} = {5'd27, 5'd28, 5'd3, 64'h12345678, 1'b0};
      #4;
      passTest(BusA, 64'd27, "Initial Value Check 27", passed);
      passTest(BusB, 64'd28, "Initial Value Check 28", passed);
      #6; Clk = 0; #10; Clk = 1;
      passTest(BusA, 64'd27, "Value Not Updated 14", passed);
      passTest(BusB, 64'd28, "Value Stayed Same 14", passed);

      {RA, RB, RW, BusW, RegWr} = {5'd29, 5'd30, 5'd3, 64'h12345678, 1'b0};
      #4;
      passTest(BusA, 64'd29, "Initial Value Check 29", passed);
      passTest(BusB, 64'd30, "Initial Value Check 30", passed);
      #6; Clk = 0; #10; Clk = 1;
      passTest(BusA, 64'd29, "Value Not Updated 15", passed);
      passTest(BusB, 64'd30, "Value Stayed Same 15", passed);

      {RA, RB, RW, BusW, RegWr} = {5'd31, 5'd31, 5'd3, 64'h12345678, 1'b0};
      #4;
      passTest(BusA, 64'd0, "Initial Value Check 31", passed);
      #6; Clk = 0; #10; Clk = 1;
      passTest(BusA, 64'd0, "Value Not Updated 16", passed);

      // Custom tests
      $display("Clearing Regs:");
      // This segment clears all registers
      {RA, RB, RW, BusW, RegWr} = {5'd0, 5'd0, 5'd0, 64'h0, 1'b1};#10; Clk = 0; #10; Clk = 1;
      {RA, RB, RW, BusW, RegWr} = {5'd0, 5'd0, 5'd1, 64'h1, 1'b1};#10; Clk = 0; #10; Clk = 1;
      {RA, RB, RW, BusW, RegWr} = {5'd0, 5'd0, 5'd2, 64'h2, 1'b1};#10; Clk = 0; #10; Clk = 1;
      {RA, RB, RW, BusW, RegWr} = {5'd0, 5'd0, 5'd3, 64'h3, 1'b1};#10; Clk = 0; #10; Clk = 1;
      {RA, RB, RW, BusW, RegWr} = {5'd0, 5'd0, 5'd4, 64'h4, 1'b1};#10; Clk = 0; #10; Clk = 1;
      {RA, RB, RW, BusW, RegWr} = {5'd0, 5'd0, 5'd5, 64'h5, 1'b1};#10; Clk = 0; #10; Clk = 1;
      {RA, RB, RW, BusW, RegWr} = {5'd0, 5'd0, 5'd6, 64'h6, 1'b1};#10; Clk = 0; #10; Clk = 1;
      {RA, RB, RW, BusW, RegWr} = {5'd0, 5'd0, 5'd7, 64'h7, 1'b1};#10; Clk = 0; #10; Clk = 1;
      {RA, RB, RW, BusW, RegWr} = {5'd0, 5'd0, 5'd8, 64'h8, 1'b1};#10; Clk = 0; #10; Clk = 1;
      {RA, RB, RW, BusW, RegWr} = {5'd0, 5'd0, 5'd9, 64'h9, 1'b1};#10; Clk = 0; #10; Clk = 1;
      {RA, RB, RW, BusW, RegWr} = {5'd0, 5'd0, 5'd10, 64'd10, 1'b1};#10; Clk = 0; #10; Clk = 1;
      {RA, RB, RW, BusW, RegWr} = {5'd0, 5'd0, 5'd11, 64'd11, 1'b1};#10; Clk = 0; #10; Clk = 1;
      {RA, RB, RW, BusW, RegWr} = {5'd0, 5'd0, 5'd12, 64'd12, 1'b1};#10; Clk = 0; #10; Clk = 1;
      {RA, RB, RW, BusW, RegWr} = {5'd0, 5'd0, 5'd13, 64'd13, 1'b1};#10; Clk = 0; #10; Clk = 1;
      {RA, RB, RW, BusW, RegWr} = {5'd0, 5'd0, 5'd14, 64'd14, 1'b1};#10; Clk = 0; #10; Clk = 1;
      {RA, RB, RW, BusW, RegWr} = {5'd0, 5'd0, 5'd15, 64'd15, 1'b1};#10; Clk = 0; #10; Clk = 1;
      {RA, RB, RW, BusW, RegWr} = {5'd0, 5'd0, 5'd16, 64'd16, 1'b1};#10; Clk = 0; #10; Clk = 1;
      {RA, RB, RW, BusW, RegWr} = {5'd0, 5'd0, 5'd17, 64'd17, 1'b1};#10; Clk = 0; #10; Clk = 1;
      {RA, RB, RW, BusW, RegWr} = {5'd0, 5'd0, 5'd18, 64'd18, 1'b1};#10; Clk = 0; #10; Clk = 1;
      {RA, RB, RW, BusW, RegWr} = {5'd0, 5'd0, 5'd19, 64'd19, 1'b1};#10; Clk = 0; #10; Clk = 1;
      {RA, RB, RW, BusW, RegWr} = {5'd0, 5'd0, 5'd20, 64'd20, 1'b1};#10; Clk = 0; #10; Clk = 1;
      {RA, RB, RW, BusW, RegWr} = {5'd0, 5'd0, 5'd21, 64'd21, 1'b1};#10; Clk = 0; #10; Clk = 1;
      {RA, RB, RW, BusW, RegWr} = {5'd0, 5'd0, 5'd22, 64'd22, 1'b1};#10; Clk = 0; #10; Clk = 1;
      {RA, RB, RW, BusW, RegWr} = {5'd0, 5'd0, 5'd23, 64'd23, 1'b1};#10; Clk = 0; #10; Clk = 1;
      {RA, RB, RW, BusW, RegWr} = {5'd0, 5'd0, 5'd24, 64'd24, 1'b1};#10; Clk = 0; #10; Clk = 1;
      {RA, RB, RW, BusW, RegWr} = {5'd0, 5'd0, 5'd25, 64'd25, 1'b1};#10; Clk = 0; #10; Clk = 1;
      {RA, RB, RW, BusW, RegWr} = {5'd0, 5'd0, 5'd26, 64'd26, 1'b1};#10; Clk = 0; #10; Clk = 1;
      {RA, RB, RW, BusW, RegWr} = {5'd0, 5'd0, 5'd27, 64'd27, 1'b1};#10; Clk = 0; #10; Clk = 1;
      {RA, RB, RW, BusW, RegWr} = {5'd0, 5'd0, 5'd28, 64'd28, 1'b1};#10; Clk = 0; #10; Clk = 1;
      {RA, RB, RW, BusW, RegWr} = {5'd0, 5'd0, 5'd29, 64'd29, 1'b1};#10; Clk = 0; #10; Clk = 1;
      {RA, RB, RW, BusW, RegWr} = {5'd0, 5'd0, 5'd30, 64'd30, 1'b1};#10; Clk = 0; #10; Clk = 1;
      {RA, RB, RW, BusW, RegWr} = {5'd0, 5'd0, 5'd31, 64'd31, 1'b1};#10; Clk = 0; #10; Clk = 1;
      
      $display("Custom tests:");
      {RA, RB, RW, BusW, RegWr} = {5'd0, 5'd1, 5'd0, 64'h0, 1'b0};
      #4;
      passTest(BusA, 64'd0, "Initial Value Check 0", passed);
      passTest(BusB, 64'd1, "Initial Value Check 1", passed);
      #6; Clk = 0; #10; Clk = 1;
      passTest(BusA, 64'd0, "Value Updated 17", passed);
      passTest(BusB, 64'd1, "Value Stayed Same 17", passed);

      {RA, RB, RW, BusW, RegWr} = {5'd2, 5'd3, 5'd1, 64'h1000, 1'b0};
      #4;
      passTest(BusA, 64'd2, "Initial Value Check 2", passed);
      passTest(BusB, 64'd3, "Initial Value Check 3", passed);
      #6; Clk = 0; #10; Clk = 1;
      passTest(BusA, 64'd2, "Value Updated 18", passed);
      passTest(BusB, 64'd3, "Value Stayed Same 18", passed);

      {RA, RB, RW, BusW, RegWr} = {5'd4, 5'd5, 5'd0, 64'h1000, 1'b1};
      #4;
      passTest(BusA, 64'd4, "Initial Value Check 4", passed);
      passTest(BusB, 64'd5, "Initial Value Check 5", passed);
      #6; Clk = 0; #10; Clk = 1;
      passTest(BusA, 64'd4, "Value Updated 19", passed);
      passTest(BusB, 64'd5, "Value Stayed Same 19", passed);

      {RA, RB, RW, BusW, RegWr} = {5'd6, 5'd7, 5'd10, 64'h1010, 1'b1};
      #4;
      passTest(BusA, 64'd6, "Initial Value Check 6", passed);
      passTest(BusB, 64'd7, "Initial Value Check 7", passed);
      #6; Clk = 0; #10; Clk = 1;
      passTest(BusA, 64'd6, "Value Updated 20", passed);
      passTest(BusB, 64'd7, "Value Stayed Same 20", passed);

      {RA, RB, RW, BusW, RegWr} = {5'd8, 5'd9, 5'd11, 64'h103000, 1'b1};
      #4;
      passTest(BusA, 64'd8, "Initial Value Check 8", passed);
      passTest(BusB, 64'd9, "Initial Value Check 9", passed);
      #6; Clk = 0; #10; Clk = 1;
      passTest(BusA, 64'd8, "Value Updated 21", passed);
      passTest(BusB, 64'd9, "Value Stayed Same 21", passed);

      {RA, RB, RW, BusW, RegWr} = {5'd10, 5'd11, 5'd12, 64'h0, 1'b0};
      #4;
      passTest(BusA, 64'h1010, "Initial Value Check 10", passed);
      passTest(BusB, 64'h103000, "Initial Value Check 11", passed);
      #6; Clk = 0; #10; Clk = 1;
      passTest(BusA, 64'h1010, "Value Updated 22", passed);
      passTest(BusB, 64'h103000, "Value Stayed Same 22", passed);

      {RA, RB, RW, BusW, RegWr} = {5'd12, 5'd13, 5'd13, 64'hABCD, 1'b1};
      #4;
      passTest(BusA, 64'd12, "Initial Value Check 12", passed);
      passTest(BusB, 64'd13, "Initial Value Check 13", passed);
      #6; Clk = 0; #10; Clk = 1;
      passTest(BusA, 64'd12, "Value Updated 23", passed);
      passTest(BusB, 64'd43981, "Value Stayed Same 23", passed);

      {RA, RB, RW, BusW, RegWr} = {5'd14, 5'd15, 5'd14, 64'h9080009, 1'b0};
      #4;
      passTest(BusA, 64'd14, "Initial Value Check 14", passed);
      passTest(BusB, 64'd15, "Initial Value Check 15", passed);
      #6; Clk = 0; #10; Clk = 1;
      passTest(BusA, 64'd14, "Value Updated 24", passed);
      passTest(BusB, 64'd15, "Value Stayed Same 24", passed);
      // End custom tests

      allPassed(passed, 100);
   end
   
endmodule

Lab08/RegisterFileTest.vcd
$date
	Tue Nov 15 19:18:09 2022
$end
$version
	Icarus Verilog
$end
$timescale
	1ps
$end
$scope module RegisterFileTest_v $end
$var wire 64 ! BusB [63:0] $end
$var wire 64 " BusA [63:0] $end
$var reg 64 # BusW [63:0] $end
$var reg 1 $ Clk $end
$var reg 5 % RA [4:0] $end
$var reg 5 & RB [4:0] $end
$var reg 5 ' RW [4:0] $end
$var reg 1 ( RegWr $end
$var reg 8 ) passed [7:0] $end
$scope module uut $end
$var wire 64 * BusW [63:0] $end
$var wire 1 $ Clk $end
$var wire 5 + RA [4:0] $end
$var wire 5 , RB [4:0] $end
$var wire 5 - RW [4:0] $end
$var wire 1 ( RegWr $end
$var wire 64 . BusB [63:0] $end
$var wire 64 / BusA [63:0] $end
$upscope $end
$scope task allPassed $end
$var reg 8 0 numTests [7:0] $end
$var reg 8 1 passed [7:0] $end
$upscope $end
$scope task passTest $end
$var reg 64 2 actualOut [63:0] $end
$var reg 64 3 expectedOut [63:0] $end
$var reg 8 4 passed [7:0] $end
$var reg 257 5 testType [256:0] $end
$upscope $end
$upscope $end
$enddefinitions $end
#0
$dumpvars
bx 5
bx 4
bx 3
bx 2
bx 1
bx 0
bx /
bx .
b0 -
b0 ,
b0 +
b0 *
b0 )
0(
b0 '
b0 &
b0 %
1$
b0 #
bx "
bx !
$end
#10000
b11111 %
b11111 +
b11111 &
b11111 ,
b11111 '
b11111 -
#12000
b0 "
b0 /
b0 !
b0 .
#20000
b10 )
b10 4
b10010010110111001101001011101000110100101100001011011000010000000100100001100000010000001000011011010000110010101100011011010110010000000110010 5
b0 3
b0 2
#30000
0$
#40000
b100 )
b100 4
b10010010110111001101001011101000110100101100001011011000010000000100100001100000010000001000011011010000110010101100011011010110010000000110100 5
b10010001101000101011001111000 #
b10010001101000101011001111000 *
1(
1$
#50000
0$
#60000
b0 %
b0 +
b0 &
b0 ,
b0 '
b0 -
b0 #
b0 *
b110 )
b110 4
b1001000011000000100000010100110111010001100001011110010111001100100000001100000010000001000011011010000110010101100011011010110010000000110010 5
1$
#62000
bx "
bx /
bx !
bx .
#70000
0$
#75000
b0 "
b0 /
b0 !
b0 .
#80000
b1 '
b1 -
b1 #
b1 *
1$
#90000
0$
#100000
b10 '
b10 -
b10 #
b10 *
1$
#110000
0$
#120000
b11 '
b11 -
b11 #
b11 *
1$
#130000
0$
#140000
b100 '
b100 -
b100 #
b100 *
1$
#150000
0$
#160000
b101 '
b101 -
b101 #
b101 *
1$
#170000
0$
#180000
b110 '
b110 -
b110 #
b110 *
1$
#190000
0$
#200000
b111 '
b111 -
b111 #
b111 *
1$
#210000
0$
#220000
b1000 '
b1000 -
b1000 #
b1000 *
1$
#230000
0$
#240000
b1001 '
b1001 -
b1001 #
b1001 *
1$
#250000
0$
#260000
b1010 '
b1010 -
b1010 #
b1010 *
1$
#270000
0$
#280000
b1011 '
b1011 -
b1011 #
b1011 *
1$
#290000
0$
#300000
b1100 '
b1100 -
b1100 #
b1100 *
1$
#310000
0$
#320000
b1101 '
b1101 -
b1101 #
b1101 *
1$
#330000
0$
#340000
b1110 '
b1110 -
b1110 #
b1110 *
1$
#350000
0$
#360000
b1111 '
b1111 -
b1111 #
b1111 *
1$
#370000
0$
#380000
b10000 '
b10000 -
b10000 #
b10000 *
1$
#390000
0$
#400000
b10001 '
b10001 -
b10001 #
b10001 *
1$
#410000
0$
#420000
b10010 '
b10010 -
b10010 #
b10010 *
1$
#430000
0$
#440000
b10011 '
b10011 -
b10011 #
b10011 *
1$
#450000
0$
#460000
b10100 '
b10100 -
b10100 #
b10100 *
1$
#470000
0$
#480000
b10101 '
b10101 -
b10101 #
b10101 *
1$
#490000
0$
#500000
b10110 '
b10110 -
b10110 #
b10110 *
1$
#510000
0$
#520000
b10111 '
b10111 -
b10111 #
b10111 *
1$
#530000
0$
#540000
b11000 '
b11000 -
b11000 #
b11000 *
1$
#550000
0$
#560000
b11001 '
b11001 -
b11001 #
b11001 *
1$
#570000
0$
#580000
b11010 '
b11010 -
b11010 #
b11010 *
1$
#590000
0$
#600000
b11011 '
b11011 -
b11011 #
b11011 *
1$
#610000
0$
#620000
b11100 '
b11100 -
b11100 #
b11100 *
1$
#630000
0$
#640000
b11101 '
b11101 -
b11101 #
b11101 *
1$
#650000
0$
#660000
b11110 '
b11110 -
b11110 #
b11110 *
1$
#670000
0$
#680000
b11111 '
b11111 -
b11111 #
b11111 *
1$
#690000
0$
#700000
b1 %
b1 +
b10 &
b10 ,
b1 '
b1 -
b10010001101000101011001111000 #
b10010001101000101011001111000 *
1$
#702000
b1 "
b1 /
b10 !
b10 .
#704000
b1000 )
b1000 4
b10010010110111001101001011101000110100101100001011011000010000001010110011000010110110001110101011001010010000001000011011010000110010101100011011010110010000000110010 5
b10 3
b10 2
#710000
0$
#715000
b10010001101000101011001111000 "
b10010001101000101011001111000 /
#720000
b11 %
b11 +
b100 &
b100 ,
b11 '
b11 -
0(
b1010 )
b1010 4
b1010110011000010110110001110101011001010010000001010011011101000110000101111001011001010110010000100000010100110110000101101101011001010010000000110001 5
b10 3
b10 2
1$
#722000
b11 "
b11 /
b100 !
b100 .
#724000
b1100 )
b1100 4
b10010010110111001101001011101000110100101100001011011000010000001010110011000010110110001110101011001010010000001000011011010000110010101100011011010110010000000110100 5
b100 3
b100 2
#730000
0$
#740000
b101 %
b101 +
b110 &
b110 ,
b1110 )
b1110 4
b1010110011000010110110001110101011001010010000001010011011101000110000101111001011001010110010000100000010100110110000101101101011001010010000000110010 5
b100 3
b100 2
1$
#742000
b101 "
b101 /
b110 !
b110 .
#744000
b10000 )
b10000 4
b10010010110111001101001011101000110100101100001011011000010000001010110011000010110110001110101011001010010000001000011011010000110010101100011011010110010000000110110 5
b110 3
b110 2
#750000
0$
#760000
b111 %
b111 +
b1000 &
b1000 ,
b10010 )
b10010 4
b1010110011000010110110001110101011001010010000001010011011101000110000101111001011001010110010000100000010100110110000101101101011001010010000000110011 5
b110 3
b110 2
1$
#762000
b111 "
b111 /
b1000 !
b1000 .
#764000
b10100 )
b10100 4
b10010010110111001101001011101000110100101100001011011000010000001010110011000010110110001110101011001010010000001000011011010000110010101100011011010110010000000111000 5
b1000 3
b1000 2
#770000
0$
#780000
b1001 %
b1001 +
b1010 &
b1010 ,
b10110 )
b10110 4
b1010110011000010110110001110101011001010010000001010011011101000110000101111001011001010110010000100000010100110110000101101101011001010010000000110100 5
b1000 3
b1000 2
1$
#782000
b1001 "
b1001 /
b1010 !
b1010 .
#784000
b11000 )
b11000 4
b1001001011011100110100101110100011010010110000101101100001000000101011001100001011011000111010101100101001000000100001101101000011001010110001101101011001000000011000100110000 5
b1010 3
b1010 2
#790000
0$
#800000
b1011 %
b1011 +
b1100 &
b1100 ,
b11010 )
b11010 4
b1010110011000010110110001110101011001010010000001010011011101000110000101111001011001010110010000100000010100110110000101101101011001010010000000110101 5
b1010 3
b1010 2
1$
#802000
b1011 "
b1011 /
b1100 !
b1100 .
#804000
b11100 )
b11100 4
b1001001011011100110100101110100011010010110000101101100001000000101011001100001011011000111010101100101001000000100001101101000011001010110001101101011001000000011000100110010 5
b1100 3
b1100 2
#810000
0$
#820000
b1101 %
b1101 +
b1110 &
b1110 ,
b11110 )
b11110 4
b1010110011000010110110001110101011001010010000001010011011101000110000101111001011001010110010000100000010100110110000101101101011001010010000000110110 5
b1100 3
b1100 2
1$
#822000
b1101 "
b1101 /
b1110 !
b1110 .
#824000
b100000 )
b100000 4
b1001001011011100110100101110100011010010110000101101100001000000101011001100001011011000111010101100101001000000100001101101000011001010110001101101011001000000011000100110100 5
b1110 3
b1110 2
#830000
0$
